sigma/__init__.py
sigma/sigma1.py
secaprpr-0.0.2.dist-info/LICENSE
secaprpr-0.0.2.dist-info/METADATA
secaprpr-0.0.2.dist-info/WHEEL
secaprpr-0.0.2.dist-info/top_level.txt
secaprpr-0.0.2.dist-info/RECORD
