Metadata-Version: 2.1
Name: secaprpr
Version: 0.0.2
Summary: six sigma project
Author: AlanRick
Author-email: zs13128488417@gmail.com
Classifier: Programming Language :: Python :: 3
Classifier: License :: OSI Approved :: MIT License
Classifier: Operating System :: OS Independent
Requires-Python: >=3.6
License-File: LICENSE
